Metadata-Version: 2.1
Name: eventos-euskadi
Version: 1.2
Summary: Paquete para interpretación de datos de Eventos en Euskadi
Home-page: https://github.com/naroabarrutia/eventos_euskadi
Author: Mikel Madariaga & Naroa Barrutia
Author-email: naroa.barrutia@alumni.mondragon.edu
License: MIT
Download-URL: https://github.com/naroabarrutia/eventos_euskadi/archive/refs/tags/v_1.2.tar.gz
Keywords: Eventos,Euskadi,Opendata
Platform: UNKNOWN
Classifier: Development Status :: 3 - Alpha
Classifier: Intended Audience :: Developers
Classifier: Topic :: Software Development :: Build Tools
Classifier: License :: OSI Approved :: MIT License
Classifier: Programming Language :: Python :: 3
Classifier: Programming Language :: Python :: 3.7
Classifier: Programming Language :: Python :: 3.8
Classifier: Programming Language :: Python :: 3.9
License-File: LICENSE.txt
